ylz_translate/.DS_Store
ylz_translate/__init__.py
ylz_translate/cli/__init__.py
ylz_translate/cli/clear_task.py
ylz_translate/cli/display_result.py
ylz_translate/cli/fix_dict.py
ylz_translate/cli/init.py
ylz_translate/cli/main.py
ylz_translate/cli/reset.py
ylz_translate/cli/start.py
ylz_translate/cli/sync_dict.py
ylz_translate/cli/test.py
ylz_translate/config.yaml
ylz_translate/llava.py
ylz_translate/pick_image.py
ylz_translate/test/.DS_Store
ylz_translate/test/20240629-json/accept.json
ylz_translate/test/20240629-json/accesstokenapp.json
ylz_translate/test/20240629-json/authconsult.json
ylz_translate/test/20240629-json/authrevocation.json
ylz_translate/test/20240629-json/capture.json
ylz_translate/test/20240629-json/change_sub.json
ylz_translate/test/20240629-json/create_sub.json
ylz_translate/test/20240629-json/createpaymentsession_easypay.json
ylz_translate/test/20240629-json/declare.json
ylz_translate/test/20240629-json/download.json
ylz_translate/test/20240629-json/inquire_vaulting.json
ylz_translate/test/20240629-json/inquirydeclare.json
ylz_translate/test/20240629-json/ir_online.json
ylz_translate/test/20240629-json/notify_capture.json
ylz_translate/test/20240629-json/notify_dispute.json
ylz_translate/test/20240629-json/notify_refund.json
ylz_translate/test/20240629-json/notify_sub.json
ylz_translate/test/20240629-json/notify_vaulting.json
ylz_translate/test/20240629-json/notifyauth.json
ylz_translate/test/20240629-json/payment_agreement.json
ylz_translate/test/20240629-json/payment_cashier.json
ylz_translate/test/20240629-json/paymentc_online.json
ylz_translate/test/20240629-json/paymentri_online.json
ylz_translate/test/20240629-json/paymentrn_online.json
ylz_translate/test/20240629-json/refund_online.json
ylz_translate/test/20240629-json/session_cashier.json
ylz_translate/test/20240629-json/supply_evidence.json
ylz_translate/test/20240629-json/vault_method.json
ylz_translate/test/20240629-json/vaulting_session.json
ylz_translate/test/20240629-json-URL.zip
ylz_translate-0.2.7.dist-info/METADATA
ylz_translate-0.2.7.dist-info/WHEEL
ylz_translate-0.2.7.dist-info/entry_points.txt
ylz_translate-0.2.7.dist-info/RECORD
