Metadata-Version: 2.1
Name: ylz-translate
Version: 0.2.7
Summary: 渐进式文档翻译系统-v2
Author: toney88
Requires-Python: >=3.10,<3.13
Classifier: Programming Language :: Python :: 3
Classifier: Programming Language :: Python :: 3.10
Classifier: Programming Language :: Python :: 3.11
Classifier: Programming Language :: Python :: 3.12
Requires-Dist: argparse (>=1.4.0,<2.0.0)
Requires-Dist: firecrawl-py (>=0.0.16,<0.0.17)
Requires-Dist: pyyaml (>=6.0.1,<7.0.0)
Requires-Dist: tqdm (>=4.66.4,<5.0.0)
Requires-Dist: ylz-utils (>=0.1.13,<0.2.0)
